[
  {
    "ion_id": 2393,
    "start_frame": 26,
    "exit_frame": 468,
    "total_time": 442
  },
  {
    "ion_id": 2307,
    "start_frame": 95,
    "exit_frame": 96,
    "total_time": 1
  },
  {
    "ion_id": 2331,
    "start_frame": 100,
    "exit_frame": 105,
    "total_time": 5
  },
  {
    "ion_id": 2344,
    "start_frame": 177,
    "exit_frame": 384,
    "total_time": 207
  },
  {
    "ion_id": 2515,
    "start_frame": 233,
    "exit_frame": 234,
    "total_time": 1
  },
  {
    "ion_id": 2392,
    "start_frame": 299,
    "exit_frame": 300,
    "total_time": 1
  },
  {
    "ion_id": 2318,
    "start_frame": 377,
    "exit_frame": 378,
    "total_time": 1
  },
  {
    "ion_id": 2398,
    "start_frame": 581,
    "exit_frame": 590,
    "total_time": 9
  },
  {
    "ion_id": 2400,
    "start_frame": 602,
    "exit_frame": 603,
    "total_time": 1
  },
  {
    "ion_id": 2288,
    "start_frame": 611,
    "exit_frame": 612,
    "total_time": 1
  },
  {
    "ion_id": 2386,
    "start_frame": 670,
    "exit_frame": 727,
    "total_time": 57
  },
  {
    "ion_id": 2399,
    "start_frame": 704,
    "exit_frame": 762,
    "total_time": 58
  },
  {
    "ion_id": 2273,
    "start_frame": 712,
    "exit_frame": 713,
    "total_time": 1
  },
  {
    "ion_id": 2240,
    "start_frame": 736,
    "exit_frame": 737,
    "total_time": 1
  },
  {
    "ion_id": 2521,
    "start_frame": 783,
    "exit_frame": 784,
    "total_time": 1
  },
  {
    "ion_id": 2302,
    "start_frame": 787,
    "exit_frame": 788,
    "total_time": 1
  },
  {
    "ion_id": 2391,
    "start_frame": 788,
    "exit_frame": 790,
    "total_time": 2
  },
  {
    "ion_id": 2520,
    "start_frame": 796,
    "exit_frame": 799,
    "total_time": 3
  },
  {
    "ion_id": 2247,
    "start_frame": 804,
    "exit_frame": 805,
    "total_time": 1
  },
  {
    "ion_id": 2231,
    "start_frame": 810,
    "exit_frame": 811,
    "total_time": 1
  },
  {
    "ion_id": 2401,
    "start_frame": 1052,
    "exit_frame": 1054,
    "total_time": 2
  },
  {
    "ion_id": 2269,
    "start_frame": 1056,
    "exit_frame": 1058,
    "total_time": 2
  },
  {
    "ion_id": 2260,
    "start_frame": 1115,
    "exit_frame": 1117,
    "total_time": 2
  },
  {
    "ion_id": 2282,
    "start_frame": 1145,
    "exit_frame": 1147,
    "total_time": 2
  },
  {
    "ion_id": 2397,
    "start_frame": 1175,
    "exit_frame": 1176,
    "total_time": 1
  },
  {
    "ion_id": 2324,
    "start_frame": 1177,
    "exit_frame": 1178,
    "total_time": 1
  },
  {
    "ion_id": 2245,
    "start_frame": 1180,
    "exit_frame": 1182,
    "total_time": 2
  },
  {
    "ion_id": 2343,
    "start_frame": 1204,
    "exit_frame": 1206,
    "total_time": 2
  },
  {
    "ion_id": 2515,
    "start_frame": 1237,
    "exit_frame": 1242,
    "total_time": 5
  }
]