{
  "130, 780": {
    "count": 1,
    "permeated_residues": [
      130
    ],
    "frames": [
      3630
    ]
  },
  "455": {
    "count": 1,
    "permeated_residues": [
      455
    ],
    "frames": [
      3666
    ]
  },
  "780, 1073": {
    "count": 1,
    "permeated_residues": [
      780
    ],
    "frames": [
      5130
    ]
  },
  "130, 1073": {
    "count": 1,
    "permeated_residues": [
      130
    ],
    "frames": [
      4415
    ]
  },
  "780, 1073, 1105": {
    "count": 1,
    "permeated_residues": [
      1105
    ],
    "frames": [
      4994
    ]
  },
  "130, 455, 780": {
    "count": 2,
    "permeated_residues": [
      130,
      130
    ],
    "frames": [
      5269,
      6424
    ]
  },
  "130, 1073, 1105": {
    "count": 1,
    "permeated_residues": [
      1105
    ],
    "frames": [
      5399
    ]
  },
  "423, 748, 780, 1073": {
    "count": 1,
    "permeated_residues": [
      780
    ],
    "frames": [
      5677
    ]
  },
  "423, 1073, 1105": {
    "count": 2,
    "permeated_residues": [
      1105,
      1105
    ],
    "frames": [
      5329,
      5433
    ]
  },
  "130, 423, 748, 1073": {
    "count": 2,
    "permeated_residues": [
      130,
      130
    ],
    "frames": [
      5886,
      6561
    ]
  },
  "98, 130, 748, 780, 1073": {
    "count": 1,
    "permeated_residues": [
      130
    ],
    "frames": [
      6016
    ]
  },
  "423, 748, 1073, 1105": {
    "count": 1,
    "permeated_residues": [
      1105
    ],
    "frames": [
      5581
    ]
  },
  "423, 748, 780, 1073, SF": {
    "count": 1,
    "permeated_residues": [
      780
    ],
    "frames": [
      6202
    ]
  },
  "130, 780, 1073, SF": {
    "count": 1,
    "permeated_residues": [
      "SF"
    ],
    "frames": [
      6487
    ]
  },
  "130, 780, 1073, 1105": {
    "count": 1,
    "permeated_residues": [
      1105
    ],
    "frames": [
      6359
    ]
  },
  "98, 423, 780, 1073": {
    "count": 4,
    "permeated_residues": [
      1073,
      98,
      780,
      423
    ],
    "frames": [
      6798,
      6798,
      6798,
      6798
    ]
  },
  "98, 130, 130, 423, 780": {
    "count": 1,
    "permeated_residues": [
      130
    ],
    "frames": [
      6727
    ]
  },
  "98, 130, 423, 1073": {
    "count": 1,
    "permeated_residues": [
      130
    ],
    "frames": [
      6670
    ]
  },
  "98, 130, 455, 780": {
    "count": 1,
    "permeated_residues": [
      780
    ],
    "frames": [
      6748
    ]
  }
}