{
  "1327": [
    {
      "residue": 98,
      "start": 6700,
      "end": 6757,
      "frames": 58,
      "mean_distance": 4.151475441866908
    },
    {
      "residue": "SF",
      "start": 6758,
      "end": 6758,
      "frames": 1,
      "mean_distance": 6.469415783882141
    },
    {
      "residue": 780,
      "start": 6759,
      "end": 6760,
      "frames": 2,
      "mean_distance": 6.989284515380859
    },
    {
      "residue": "SF",
      "start": 6761,
      "end": 6761,
      "frames": 1,
      "mean_distance": 8.433125376701355
    },
    {
      "residue": 780,
      "start": 6762,
      "end": 6762,
      "frames": 1,
      "mean_distance": 6.787091255187988
    },
    {
      "residue": 455,
      "start": 6763,
      "end": 6763,
      "frames": 1,
      "mean_distance": 8.160333633422852
    },
    {
      "residue": 748,
      "start": 6764,
      "end": 6764,
      "frames": 1,
      "mean_distance": 7.076866149902344
    },
    {
      "residue": 780,
      "start": 6765,
      "end": 6765,
      "frames": 1,
      "mean_distance": 7.921586990356445
    },
    {
      "residue": "SF",
      "start": 6766,
      "end": 6766,
      "frames": 1,
      "mean_distance": 7.21702253818512
    },
    {
      "residue": 780,
      "start": 6767,
      "end": 6767,
      "frames": 1,
      "mean_distance": 7.151012420654297
    },
    {
      "residue": 1105,
      "start": 6768,
      "end": 6768,
      "frames": 1,
      "mean_distance": 7.557670593261719
    },
    {
      "residue": 780,
      "start": 6769,
      "end": 6771,
      "frames": 3,
      "mean_distance": 6.078268210093181
    },
    {
      "residue": 1105,
      "start": 6772,
      "end": 6772,
      "frames": 1,
      "mean_distance": 6.191177845001221
    },
    {
      "residue": "SF",
      "start": 6773,
      "end": 6773,
      "frames": 1,
      "mean_distance": 7.903006553649902
    },
    {
      "residue": 1105,
      "start": 6774,
      "end": 6775,
      "frames": 2,
      "mean_distance": 5.924083232879639
    },
    {
      "residue": 1073,
      "start": 6776,
      "end": 6799,
      "frames": 24,
      "mean_distance": 4.508596430222194
    }
  ],
  "1330": [
    {
      "residue": 98,
      "start": 6700,
      "end": 6700,
      "frames": 1,
      "mean_distance": 4.840076923370361
    },
    {
      "residue": 130,
      "start": 6701,
      "end": 6701,
      "frames": 1,
      "mean_distance": 6.306676864624023
    },
    {
      "residue": 98,
      "start": 6702,
      "end": 6707,
      "frames": 6,
      "mean_distance": 4.768552939097087
    },
    {
      "residue": 130,
      "start": 6708,
      "end": 6709,
      "frames": 2,
      "mean_distance": 4.5441813468933105
    },
    {
      "residue": 98,
      "start": 6710,
      "end": 6711,
      "frames": 2,
      "mean_distance": 4.524889230728149
    },
    {
      "residue": 130,
      "start": 6712,
      "end": 6712,
      "frames": 1,
      "mean_distance": 4.736915111541748
    },
    {
      "residue": 98,
      "start": 6713,
      "end": 6713,
      "frames": 1,
      "mean_distance": 4.799172878265381
    },
    {
      "residue": 130,
      "start": 6714,
      "end": 6714,
      "frames": 1,
      "mean_distance": 4.601632118225098
    },
    {
      "residue": 98,
      "start": 6715,
      "end": 6715,
      "frames": 1,
      "mean_distance": 4.648920059204102
    },
    {
      "residue": 130,
      "start": 6716,
      "end": 6716,
      "frames": 1,
      "mean_distance": 4.709935188293457
    },
    {
      "residue": 98,
      "start": 6717,
      "end": 6720,
      "frames": 4,
      "mean_distance": 4.971604108810425
    },
    {
      "residue": 130,
      "start": 6721,
      "end": 6722,
      "frames": 2,
      "mean_distance": 5.177355051040649
    },
    {
      "residue": 98,
      "start": 6723,
      "end": 6723,
      "frames": 1,
      "mean_distance": 5.066906452178955
    },
    {
      "residue": 130,
      "start": 6724,
      "end": 6724,
      "frames": 1,
      "mean_distance": 5.058986663818359
    },
    {
      "residue": 98,
      "start": 6725,
      "end": 6726,
      "frames": 2,
      "mean_distance": 5.0709004402160645
    },
    {
      "residue": 130,
      "start": 6727,
      "end": 6728,
      "frames": 2,
      "mean_distance": 5.127826690673828
    },
    {
      "residue": 98,
      "start": 6729,
      "end": 6729,
      "frames": 1,
      "mean_distance": 4.946806907653809
    },
    {
      "residue": 130,
      "start": 6730,
      "end": 6730,
      "frames": 1,
      "mean_distance": 5.283025741577148
    },
    {
      "residue": 98,
      "start": 6731,
      "end": 6742,
      "frames": 12,
      "mean_distance": 4.936335364977519
    },
    {
      "residue": 130,
      "start": 6743,
      "end": 6743,
      "frames": 1,
      "mean_distance": 5.027177333831787
    },
    {
      "residue": 98,
      "start": 6744,
      "end": 6744,
      "frames": 1,
      "mean_distance": 4.826062202453613
    },
    {
      "residue": 130,
      "start": 6745,
      "end": 6745,
      "frames": 1,
      "mean_distance": 5.243302345275879
    },
    {
      "residue": 98,
      "start": 6746,
      "end": 6747,
      "frames": 2,
      "mean_distance": 4.866353511810303
    },
    {
      "residue": 130,
      "start": 6748,
      "end": 6748,
      "frames": 1,
      "mean_distance": 4.764212608337402
    },
    {
      "residue": 98,
      "start": 6749,
      "end": 6754,
      "frames": 6,
      "mean_distance": 4.736954212188721
    },
    {
      "residue": 130,
      "start": 6755,
      "end": 6755,
      "frames": 1,
      "mean_distance": 4.950564861297607
    },
    {
      "residue": 98,
      "start": 6756,
      "end": 6770,
      "frames": 15,
      "mean_distance": 4.690890979766846
    },
    {
      "residue": 130,
      "start": 6771,
      "end": 6771,
      "frames": 1,
      "mean_distance": 4.702598571777344
    },
    {
      "residue": 98,
      "start": 6772,
      "end": 6798,
      "frames": 27,
      "mean_distance": 4.800301622461389
    },
    {
      "residue": 130,
      "start": 6799,
      "end": 6799,
      "frames": 1,
      "mean_distance": 4.614262104034424
    }
  ],
  "1341": [
    {
      "residue": 780,
      "start": 6700,
      "end": 6700,
      "frames": 1,
      "mean_distance": 5.773787498474121
    },
    {
      "residue": 748,
      "start": 6701,
      "end": 6705,
      "frames": 5,
      "mean_distance": 5.8486908912658695
    },
    {
      "residue": 780,
      "start": 6706,
      "end": 6709,
      "frames": 4,
      "mean_distance": 5.942062020301819
    },
    {
      "residue": 748,
      "start": 6710,
      "end": 6710,
      "frames": 1,
      "mean_distance": 7.431769371032715
    },
    {
      "residue": 780,
      "start": 6711,
      "end": 6712,
      "frames": 2,
      "mean_distance": 6.200758695602417
    },
    {
      "residue": 748,
      "start": 6713,
      "end": 6713,
      "frames": 1,
      "mean_distance": 6.912192344665527
    },
    {
      "residue": 780,
      "start": 6714,
      "end": 6715,
      "frames": 2,
      "mean_distance": 6.34295654296875
    },
    {
      "residue": 1073,
      "start": 6716,
      "end": 6716,
      "frames": 1,
      "mean_distance": 7.899685382843018
    },
    {
      "residue": 780,
      "start": 6717,
      "end": 6717,
      "frames": 1,
      "mean_distance": 5.957164287567139
    },
    {
      "residue": 748,
      "start": 6718,
      "end": 6721,
      "frames": 4,
      "mean_distance": 4.963082671165466
    },
    {
      "residue": 780,
      "start": 6722,
      "end": 6726,
      "frames": 5,
      "mean_distance": 6.441091918945313
    },
    {
      "residue": 130,
      "start": 6727,
      "end": 6727,
      "frames": 1,
      "mean_distance": 5.967150688171387
    },
    {
      "residue": 1105,
      "start": 6728,
      "end": 6728,
      "frames": 1,
      "mean_distance": 14.995952606201172
    }
  ],
  "1359": [
    {
      "residue": 423,
      "start": 6700,
      "end": 6703,
      "frames": 4,
      "mean_distance": 5.010440349578857
    },
    {
      "residue": 130,
      "start": 6704,
      "end": 6704,
      "frames": 1,
      "mean_distance": 7.30110502243042
    },
    {
      "residue": 423,
      "start": 6705,
      "end": 6739,
      "frames": 35,
      "mean_distance": 4.775311429159982
    },
    {
      "residue": 455,
      "start": 6740,
      "end": 6740,
      "frames": 1,
      "mean_distance": 5.949402332305908
    },
    {
      "residue": 423,
      "start": 6741,
      "end": 6747,
      "frames": 7,
      "mean_distance": 4.67463561466762
    },
    {
      "residue": 455,
      "start": 6748,
      "end": 6751,
      "frames": 4,
      "mean_distance": 6.308160781860352
    },
    {
      "residue": 780,
      "start": 6752,
      "end": 6752,
      "frames": 1,
      "mean_distance": 7.080137252807617
    },
    {
      "residue": 748,
      "start": 6753,
      "end": 6753,
      "frames": 1,
      "mean_distance": 8.095803260803223
    },
    {
      "residue": 455,
      "start": 6754,
      "end": 6754,
      "frames": 1,
      "mean_distance": 6.560533046722412
    },
    {
      "residue": 780,
      "start": 6755,
      "end": 6755,
      "frames": 1,
      "mean_distance": 7.180362224578857
    },
    {
      "residue": 748,
      "start": 6756,
      "end": 6757,
      "frames": 2,
      "mean_distance": 5.120666742324829
    },
    {
      "residue": 1105,
      "start": 6758,
      "end": 6758,
      "frames": 1,
      "mean_distance": 7.747400283813477
    },
    {
      "residue": 748,
      "start": 6759,
      "end": 6761,
      "frames": 3,
      "mean_distance": 7.070893923441569
    },
    {
      "residue": "SF",
      "start": 6762,
      "end": 6762,
      "frames": 1,
      "mean_distance": 6.191336989402771
    },
    {
      "residue": 1105,
      "start": 6763,
      "end": 6764,
      "frames": 2,
      "mean_distance": 6.775428295135498
    },
    {
      "residue": 748,
      "start": 6765,
      "end": 6765,
      "frames": 1,
      "mean_distance": 7.485365390777588
    },
    {
      "residue": 780,
      "start": 6766,
      "end": 6766,
      "frames": 1,
      "mean_distance": 6.353230953216553
    },
    {
      "residue": 1105,
      "start": 6767,
      "end": 6767,
      "frames": 1,
      "mean_distance": 6.85874080657959
    },
    {
      "residue": 780,
      "start": 6768,
      "end": 6768,
      "frames": 1,
      "mean_distance": 7.19215726852417
    },
    {
      "residue": 130,
      "start": 6769,
      "end": 6769,
      "frames": 1,
      "mean_distance": 6.73826789855957
    },
    {
      "residue": 748,
      "start": 6770,
      "end": 6770,
      "frames": 1,
      "mean_distance": 7.281708717346191
    },
    {
      "residue": "SF",
      "start": 6771,
      "end": 6771,
      "frames": 1,
      "mean_distance": 6.582444429397583
    },
    {
      "residue": 780,
      "start": 6772,
      "end": 6772,
      "frames": 1,
      "mean_distance": 6.653458595275879
    },
    {
      "residue": 455,
      "start": 6773,
      "end": 6773,
      "frames": 1,
      "mean_distance": 5.6332597732543945
    },
    {
      "residue": 748,
      "start": 6774,
      "end": 6780,
      "frames": 7,
      "mean_distance": 4.327977384839739
    },
    {
      "residue": 455,
      "start": 6781,
      "end": 6781,
      "frames": 1,
      "mean_distance": 7.827762126922607
    },
    {
      "residue": 780,
      "start": 6782,
      "end": 6782,
      "frames": 1,
      "mean_distance": 7.469205856323242
    },
    {
      "residue": 455,
      "start": 6783,
      "end": 6785,
      "frames": 3,
      "mean_distance": 5.627317905426025
    },
    {
      "residue": 748,
      "start": 6786,
      "end": 6786,
      "frames": 1,
      "mean_distance": 7.183438301086426
    },
    {
      "residue": 455,
      "start": 6787,
      "end": 6787,
      "frames": 1,
      "mean_distance": 6.1940178871154785
    },
    {
      "residue": 748,
      "start": 6788,
      "end": 6788,
      "frames": 1,
      "mean_distance": 7.729644298553467
    },
    {
      "residue": 780,
      "start": 6789,
      "end": 6793,
      "frames": 5,
      "mean_distance": 6.689367866516113
    },
    {
      "residue": 423,
      "start": 6794,
      "end": 6794,
      "frames": 1,
      "mean_distance": 7.544034004211426
    },
    {
      "residue": 455,
      "start": 6795,
      "end": 6797,
      "frames": 3,
      "mean_distance": 5.783557573954265
    },
    {
      "residue": 780,
      "start": 6798,
      "end": 6799,
      "frames": 2,
      "mean_distance": 6.8533666133880615
    }
  ],
  "1374": [
    {
      "residue": 780,
      "start": 6716,
      "end": 6716,
      "frames": 1,
      "mean_distance": 6.963595867156982
    },
    {
      "residue": 455,
      "start": 6717,
      "end": 6717,
      "frames": 1,
      "mean_distance": 6.120789527893066
    },
    {
      "residue": 780,
      "start": 6718,
      "end": 6718,
      "frames": 1,
      "mean_distance": 7.498498439788818
    },
    {
      "residue": 1105,
      "start": 6719,
      "end": 6719,
      "frames": 1,
      "mean_distance": 7.018267631530762
    },
    {
      "residue": 780,
      "start": 6720,
      "end": 6721,
      "frames": 2,
      "mean_distance": 6.122759819030762
    },
    {
      "residue": 1105,
      "start": 6722,
      "end": 6722,
      "frames": 1,
      "mean_distance": 7.253707408905029
    },
    {
      "residue": 748,
      "start": 6723,
      "end": 6725,
      "frames": 3,
      "mean_distance": 7.393232822418213
    },
    {
      "residue": 1105,
      "start": 6726,
      "end": 6726,
      "frames": 1,
      "mean_distance": 7.1458258628845215
    },
    {
      "residue": 780,
      "start": 6727,
      "end": 6729,
      "frames": 3,
      "mean_distance": 6.419859091440837
    },
    {
      "residue": 748,
      "start": 6730,
      "end": 6731,
      "frames": 2,
      "mean_distance": 4.551169395446777
    },
    {
      "residue": 780,
      "start": 6732,
      "end": 6733,
      "frames": 2,
      "mean_distance": 5.739436626434326
    },
    {
      "residue": "SF",
      "start": 6734,
      "end": 6734,
      "frames": 1,
      "mean_distance": 8.103137016296387
    },
    {
      "residue": 1105,
      "start": 6735,
      "end": 6735,
      "frames": 1,
      "mean_distance": 7.780446529388428
    },
    {
      "residue": 748,
      "start": 6736,
      "end": 6736,
      "frames": 1,
      "mean_distance": 5.049374103546143
    },
    {
      "residue": 780,
      "start": 6737,
      "end": 6739,
      "frames": 3,
      "mean_distance": 5.850259621938069
    },
    {
      "residue": 748,
      "start": 6740,
      "end": 6744,
      "frames": 5,
      "mean_distance": 4.917568492889404
    },
    {
      "residue": 780,
      "start": 6745,
      "end": 6745,
      "frames": 1,
      "mean_distance": 7.288521766662598
    },
    {
      "residue": 1105,
      "start": 6746,
      "end": 6746,
      "frames": 1,
      "mean_distance": 6.538213729858398
    },
    {
      "residue": 780,
      "start": 6747,
      "end": 6748,
      "frames": 2,
      "mean_distance": 6.223405838012695
    },
    {
      "residue": 130,
      "start": 6749,
      "end": 6749,
      "frames": 1,
      "mean_distance": 7.192011833190918
    }
  ],
  "1400": [
    {
      "residue": 130,
      "start": 6753,
      "end": 6753,
      "frames": 1,
      "mean_distance": 8.152956008911133
    },
    {
      "residue": 423,
      "start": 6754,
      "end": 6768,
      "frames": 15,
      "mean_distance": 5.282794761657715
    },
    {
      "residue": 455,
      "start": 6769,
      "end": 6769,
      "frames": 1,
      "mean_distance": 5.587139129638672
    },
    {
      "residue": 423,
      "start": 6770,
      "end": 6799,
      "frames": 30,
      "mean_distance": 4.680614447593689
    }
  ]
}